[ {
  "Title" : "Stranger Things",
  "Year" : "2016-2025",
  "Director" : "N/A",
  "Actors" : "Millie Bobby Brown, Finn Wolfhard, Winona Ryder",
  "Plot" : "In 1980s Indiana, a group of young friends witness supernatural forces and secret government exploits. As they search for answers, the children unravel a series of extraordinary mysteries.",
  "Poster" : "https://m.media-amazon.com/images/M/MV5BMjE2N2MyMzEtNmU5NS00OTI0LTlkNTMtMWM1YWYyNmU4NmY0XkEyXkFqcGc@._V1_SX300.jpg",
  "imdbRating" : "8.7",
  "Genre" : "Drama, Fantasy, Horror",
  "Runtime" : "51 min",
  "Country" : "United States"
} ]